fairdetect_pedro_a/__init__.py
fairdetect_pedro_a-0.1.dist-info/METADATA
fairdetect_pedro_a-0.1.dist-info/WHEEL
fairdetect_pedro_a-0.1.dist-info/top_level.txt
fairdetect_pedro_a-0.1.dist-info/RECORD
