Metadata-Version: 2.1
Name: fairdetect-pedro-a
Version: 0.1
Summary: Python Packaging Starting Kit - Simple Structure to creater your own package - for training purposes!
Home-page: https://github.com/manoelgadi/pythonpackagesample
Author: Pedro V
Author-email: pedrovesteban@student.ie.edu
License: MIT
Platform: UNKNOWN
